{"mastermndio":[{"streamer":"mastermndio","startTime":"Mon, Aug 17, 2020 10:50 PM +0000","endTime":"Tue, Aug 18, 2020 1:10 AM +0000","length":8399},{"streamer":"mastermndio","startTime":"Wed, Aug 19, 2020 11:00 PM +0000","endTime":"Thu, Aug 20, 2020 1:35 AM +0000","length":9300},{"streamer":"mastermndio","startTime":"Thu, Aug 20, 2020 10:55 PM +0000","endTime":"Fri, Aug 21, 2020 1:15 AM +0000","length":8399}],"jenninexus":[{"streamer":"jenninexus","startTime":"Thu, Aug 20, 2020 5:55 AM +0000","endTime":"Thu, Aug 20, 2020 7:46 AM +0000","length":6658}],"cldubya":[{"streamer":"cldubya","startTime":"Mon, Aug 17, 2020 9:00 PM +0000","endTime":"Tue, Aug 18, 2020 12:10 midnight +0000","length":11399},{"streamer":"cldubya","startTime":"Wed, Aug 19, 2020 5:00 PM +0000","endTime":"Wed, Aug 19, 2020 8:15 PM +0000","length":11699},{"streamer":"cldubya","startTime":"Thu, Aug 20, 2020 6:05 PM +0000","endTime":"Thu, Aug 20, 2020 8:41 PM +0000","length":9355}],"Sana_Rinomi":[{"streamer":"Sana_Rinomi","startTime":"Tue, Aug 18, 2020 5:45 PM +0000","endTime":"Tue, Aug 18, 2020 9:10 PM +0000","length":12300},{"streamer":"Sana_Rinomi","startTime":"Wed, Aug 19, 2020 5:50 PM +0000","endTime":"Wed, Aug 19, 2020 8:55 PM +0000","length":11099},{"streamer":"Sana_Rinomi","startTime":"Thu, Aug 20, 2020 5:50 PM +0000","endTime":"Thu, Aug 20, 2020 7:45 PM +0000","length":6900}],"1kevgriff":[{"streamer":"1kevgriff","startTime":"Mon, Aug 17, 2020 6:45 PM +0000","endTime":"Mon, Aug 17, 2020 9:00 PM +0000","length":8100}],"Simpathey":[{"streamer":"Simpathey","startTime":"Sun, Aug 16, 2020 8:35 PM +0000","endTime":"Sun, Aug 16, 2020 10:55 PM +0000","length":8399},{"streamer":"Simpathey","startTime":"Wed, Aug 19, 2020 3:05 AM +0000","endTime":"Wed, Aug 19, 2020 5:05 AM +0000","length":7200},{"streamer":"Simpathey","startTime":"Sun, Aug 23, 2020 2:50 AM +0000","endTime":"Sun, Aug 23, 2020 4:50 AM +0000","length":7201}],"GoPirateSoftware":[{"streamer":"GoPirateSoftware","startTime":"Mon, Aug 17, 2020 4:10 AM +0000","endTime":"Mon, Aug 17, 2020 9:20 AM +0000","length":18599},{"streamer":"GoPirateSoftware","startTime":"Tue, Aug 18, 2020 9:05 PM +0000","endTime":"Wed, Aug 19, 2020 12:10 midnight +0000","length":11099},{"streamer":"GoPirateSoftware","startTime":"Fri, Aug 21, 2020 12:15 midnight +0000","endTime":"Fri, Aug 21, 2020 5:35 AM +0000","length":19200},{"streamer":"GoPirateSoftware","startTime":"Sat, Aug 22, 2020 6:10 AM +0000","endTime":"Sat, Aug 22, 2020 11:30 AM +0000","length":19199}],"LaylaCodesIt":[{"streamer":"LaylaCodesIt","startTime":"Mon, Aug 17, 2020 2:25 PM +0000","endTime":"Mon, Aug 17, 2020 5:15 PM +0000","length":10200},{"streamer":"LaylaCodesIt","startTime":"Thu, Aug 20, 2020 1:05 PM +0000","endTime":"Thu, Aug 20, 2020 4:05 PM +0000","length":10800},{"streamer":"LaylaCodesIt","startTime":"Fri, Aug 21, 2020 1:30 PM +0000","endTime":"Fri, Aug 21, 2020 4:10 PM +0000","length":9600}],"riallymundane":[{"streamer":"riallymundane","startTime":"Sun, Aug 16, 2020 7:45 AM +0000","endTime":"Sun, Aug 16, 2020 1:15 PM +0000","length":19800},{"streamer":"riallymundane","startTime":"Mon, Aug 17, 2020 6:25 AM +0000","endTime":"Mon, Aug 17, 2020 1:15 PM +0000","length":24601},{"streamer":"riallymundane","startTime":"Wed, Aug 19, 2020 6:40 AM +0000","endTime":"Wed, Aug 19, 2020 10:45 AM +0000","length":14700},{"streamer":"riallymundane","startTime":"Thu, Aug 20, 2020 6:45 AM +0000","endTime":"Thu, Aug 20, 2020 11:10 AM +0000","length":15899},{"streamer":"riallymundane","startTime":"Fri, Aug 21, 2020 7:10 AM +0000","endTime":"Fri, Aug 21, 2020 10:20 AM +0000","length":11401},{"streamer":"riallymundane","startTime":"Sat, Aug 22, 2020 7:00 AM +0000","endTime":"Sat, Aug 22, 2020 1:10 PM +0000","length":22200}],"dansiegel":[{"streamer":"dansiegel","startTime":"Tue, Aug 18, 2020 9:35 PM +0000","endTime":"Tue, Aug 18, 2020 11:40 PM +0000","length":7499}],"polerin":[{"streamer":"polerin","startTime":"Tue, Aug 18, 2020 5:15 PM +0000","endTime":"Tue, Aug 18, 2020 6:40 PM +0000","length":5099},{"streamer":"polerin","startTime":"Wed, Aug 19, 2020 1:25 AM +0000","endTime":"Wed, Aug 19, 2020 3:30 AM +0000","length":7499},{"streamer":"polerin","startTime":"Wed, Aug 19, 2020 5:15 PM +0000","endTime":"Wed, Aug 19, 2020 6:35 PM +0000","length":4801},{"streamer":"polerin","startTime":"Thu, Aug 20, 2020 5:15 PM +0000","endTime":"Thu, Aug 20, 2020 6:25 PM +0000","length":4199},{"streamer":"polerin","startTime":"Fri, Aug 21, 2020 1:05 AM +0000","endTime":"Fri, Aug 21, 2020 4:05 AM +0000","length":10800},{"streamer":"polerin","startTime":"Fri, Aug 21, 2020 5:15 PM +0000","endTime":"Fri, Aug 21, 2020 6:20 PM +0000","length":3900}],"AlSweigart":[{"streamer":"AlSweigart","startTime":"Sun, Aug 16, 2020 4:50 PM +0000","endTime":"Sun, Aug 16, 2020 10:35 PM +0000","length":20699}],"VapeJuiceJordan":[{"streamer":"VapeJuiceJordan","startTime":"Sun, Aug 16, 2020 10:00 PM +0000","endTime":"Sun, Aug 16, 2020 11:55 PM +0000","length":6899},{"streamer":"VapeJuiceJordan","startTime":"Mon, Aug 17, 2020 6:10 PM +0000","endTime":"Mon, Aug 17, 2020 8:25 PM +0000","length":8100},{"streamer":"VapeJuiceJordan","startTime":"Wed, Aug 19, 2020 12:35 midnight +0000","endTime":"Wed, Aug 19, 2020 2:40 AM +0000","length":7499},{"streamer":"VapeJuiceJordan","startTime":"Thu, Aug 20, 2020 6:40 PM +0000","endTime":"Thu, Aug 20, 2020 9:10 PM +0000","length":8999},{"streamer":"VapeJuiceJordan","startTime":"Sat, Aug 22, 2020 1:10 AM +0000","endTime":"Sat, Aug 22, 2020 2:25 AM +0000","length":4499}],"nipafx":[{"streamer":"nipafx","startTime":"Sun, Aug 16, 2020 2:25 PM +0000","endTime":"Sun, Aug 16, 2020 6:50 PM +0000","length":15900},{"streamer":"nipafx","startTime":"Tue, Aug 18, 2020 5:00 PM +0000","endTime":"Tue, Aug 18, 2020 7:05 PM +0000","length":7499}],"SquidMonkeyStudios":[{"streamer":"SquidMonkeyStudios","startTime":"Sun, Aug 16, 2020 8:00 PM +0000","endTime":"Sun, Aug 16, 2020 10:50 PM +0000","length":10201},{"streamer":"SquidMonkeyStudios","startTime":"Tue, Aug 18, 2020 8:30 PM +0000","endTime":"Tue, Aug 18, 2020 10:50 PM +0000","length":8400},{"streamer":"SquidMonkeyStudios","startTime":"Thu, Aug 20, 2020 8:15 PM +0000","endTime":"Thu, Aug 20, 2020 10:55 PM +0000","length":9599}],"jamesqquick":[{"streamer":"jamesqquick","startTime":"Mon, Aug 17, 2020 8:50 PM +0000","endTime":"Mon, Aug 17, 2020 10:10 PM +0000","length":4801},{"streamer":"jamesqquick","startTime":"Fri, Aug 21, 2020 4:05 PM +0000","endTime":"Fri, Aug 21, 2020 5:40 PM +0000","length":5700}],"MishManners":[{"streamer":"MishManners","startTime":"Sun, Aug 16, 2020 11:30 AM +0000","endTime":"Sun, Aug 16, 2020 1:50 PM +0000","length":8399},{"streamer":"MishManners","startTime":"Mon, Aug 17, 2020 11:00 AM +0000","endTime":"Mon, Aug 17, 2020 2:15 PM +0000","length":11700},{"streamer":"MishManners","startTime":"Tue, Aug 18, 2020 9:05 AM +0000","endTime":"Tue, Aug 18, 2020 1:30 PM +0000","length":15900},{"streamer":"MishManners","startTime":"Wed, Aug 19, 2020 10:35 AM +0000","endTime":"Wed, Aug 19, 2020 3:35 PM +0000","length":18000},{"streamer":"MishManners","startTime":"Thu, Aug 20, 2020 4:25 AM +0000","endTime":"Thu, Aug 20, 2020 7:00 AM +0000","length":9301},{"streamer":"MishManners","startTime":"Fri, Aug 21, 2020 11:15 AM +0000","endTime":"Fri, Aug 21, 2020 4:20 PM +0000","length":18300},{"streamer":"MishManners","startTime":"Sat, Aug 22, 2020 9:05 AM +0000","endTime":"Sat, Aug 22, 2020 3:25 PM +0000","length":22799}],"ChaelCodes":[{"streamer":"ChaelCodes","startTime":"Sun, Aug 16, 2020 1:00 PM +0000","endTime":"Sun, Aug 16, 2020 6:25 PM +0000","length":19500},{"streamer":"ChaelCodes","startTime":"Thu, Aug 20, 2020 11:05 PM +0000","endTime":"Fri, Aug 21, 2020 2:00 AM +0000","length":10501}],"ChefBrent":[{"streamer":"ChefBrent","startTime":"Tue, Aug 18, 2020 7:45 PM +0000","endTime":"Tue, Aug 18, 2020 9:55 PM +0000","length":7801},{"streamer":"ChefBrent","startTime":"Fri, Aug 21, 2020 6:55 PM +0000","endTime":"Fri, Aug 21, 2020 9:15 PM +0000","length":8401},{"streamer":"ChefBrent","startTime":"Sat, Aug 22, 2020 1:20 AM +0000","endTime":"Sat, Aug 22, 2020 4:45 AM +0000","length":12300}],"JeffBlankenburg":[{"streamer":"JeffBlankenburg","startTime":"Mon, Aug 17, 2020 1:55 PM +0000","endTime":"Mon, Aug 17, 2020 3:40 PM +0000","length":6300}],"mbcrump":[{"streamer":"mbcrump","startTime":"Sun, Aug 16, 2020 11:30 PM +0000","endTime":"Mon, Aug 17, 2020 1:20 AM +0000","length":6599},{"streamer":"mbcrump","startTime":"Fri, Aug 21, 2020 11:10 PM +0000","endTime":"Sat, Aug 22, 2020 1:30 AM +0000","length":8399},{"streamer":"mbcrump","startTime":"Sat, Aug 22, 2020 11:00 PM +0000","endTime":"Sun, Aug 23, 2020 1:35 AM +0000","length":9299}],"theMessyCoder":[{"streamer":"theMessyCoder","startTime":"Sat, Aug 22, 2020 9:01 PM +0000","endTime":"Sat, Aug 22, 2020 11:50 PM +0000","length":10145}],"MrDemonWolf":[{"streamer":"MrDemonWolf","startTime":"Mon, Aug 17, 2020 3:55 PM +0000","endTime":"Mon, Aug 17, 2020 6:00 PM +0000","length":7499},{"streamer":"MrDemonWolf","startTime":"Mon, Aug 17, 2020 10:00 PM +0000","endTime":"Tue, Aug 18, 2020 1:10 AM +0000","length":11399},{"streamer":"MrDemonWolf","startTime":"Tue, Aug 18, 2020 4:05 PM +0000","endTime":"Tue, Aug 18, 2020 9:10 PM +0000","length":18300},{"streamer":"MrDemonWolf","startTime":"Thu, Aug 20, 2020 7:05 PM +0000","endTime":"Fri, Aug 21, 2020 12:15 midnight +0000","length":18600},{"streamer":"MrDemonWolf","startTime":"Fri, Aug 21, 2020 9:55 PM +0000","endTime":"Sat, Aug 22, 2020 12:55 midnight +0000","length":10800},{"streamer":"MrDemonWolf","startTime":"Sat, Aug 22, 2020 7:00 PM +0000","endTime":"Sat, Aug 22, 2020 10:20 PM +0000","length":12000}],"DevelopersGarage":[{"streamer":"DevelopersGarage","startTime":"Mon, Aug 17, 2020 6:05 PM +0000","endTime":"Mon, Aug 17, 2020 8:00 PM +0000","length":6901}],"Rosuav":[{"streamer":"Rosuav","startTime":"Sun, Aug 16, 2020 11:55 PM +0000","endTime":"Mon, Aug 17, 2020 4:45 AM +0000","length":17401},{"streamer":"Rosuav","startTime":"Thu, Aug 20, 2020 10:00 AM +0000","endTime":"Thu, Aug 20, 2020 12:30 noon +0000","length":9002},{"streamer":"Rosuav","startTime":"Fri, Aug 21, 2020 10:00 AM +0000","endTime":"Fri, Aug 21, 2020 1:15 PM +0000","length":11701}],"fiercekittenz":[{"streamer":"fiercekittenz","startTime":"Tue, Aug 18, 2020 12:55 midnight +0000","endTime":"Tue, Aug 18, 2020 2:50 AM +0000","length":6899},{"streamer":"fiercekittenz","startTime":"Thu, Aug 20, 2020 1:05 AM +0000","endTime":"Thu, Aug 20, 2020 3:05 AM +0000","length":7200},{"streamer":"fiercekittenz","startTime":"Fri, Aug 21, 2020 1:05 AM +0000","endTime":"Fri, Aug 21, 2020 2:55 AM +0000","length":6600}],"SudoKid":[{"streamer":"SudoKid","startTime":"Sun, Aug 16, 2020 10:50 PM +0000","endTime":"Mon, Aug 17, 2020 1:25 AM +0000","length":9301},{"streamer":"SudoKid","startTime":"Sat, Aug 22, 2020 1:40 AM +0000","endTime":"Sat, Aug 22, 2020 4:15 AM +0000","length":9300},{"streamer":"SudoKid","startTime":"Sat, Aug 22, 2020 7:55 PM +0000","endTime":"Sat, Aug 22, 2020 10:40 PM +0000","length":9900}],"JitterTed":[{"streamer":"JitterTed","startTime":"Tue, Aug 18, 2020 8:05 PM +0000","endTime":"Tue, Aug 18, 2020 10:50 PM +0000","length":9900},{"streamer":"JitterTed","startTime":"Thu, Aug 20, 2020 8:10 PM +0000","endTime":"Thu, Aug 20, 2020 11:05 PM +0000","length":10500},{"streamer":"JitterTed","startTime":"Fri, Aug 21, 2020 7:55 PM +0000","endTime":"Fri, Aug 21, 2020 11:50 PM +0000","length":14099}],"Syropian":[{"streamer":"Syropian","startTime":"Fri, Aug 21, 2020 5:25 PM +0000","endTime":"Fri, Aug 21, 2020 6:45 PM +0000","length":4800}],"DrMikachu":[{"streamer":"DrMikachu","startTime":"Wed, Aug 19, 2020 9:00 PM +0000","endTime":"Thu, Aug 20, 2020 12:50 midnight +0000","length":13800},{"streamer":"DrMikachu","startTime":"Fri, Aug 21, 2020 1:05 AM +0000","endTime":"Fri, Aug 21, 2020 4:10 AM +0000","length":11100}],"FullStackLive":[{"streamer":"FullStackLive","startTime":"Sat, Aug 22, 2020 3:00 PM +0000","endTime":"Sat, Aug 22, 2020 5:05 PM +0000","length":7500}],"Talk2meGooseman":[{"streamer":"Talk2meGooseman","startTime":"Sun, Aug 16, 2020 5:55 PM +0000","endTime":"Sun, Aug 16, 2020 8:15 PM +0000","length":8400},{"streamer":"Talk2meGooseman","startTime":"Thu, Aug 20, 2020 2:05 AM +0000","endTime":"Thu, Aug 20, 2020 5:15 AM +0000","length":11400}],"Lana_Lux":[{"streamer":"Lana_Lux","startTime":"Sun, Aug 16, 2020 1:35 PM +0000","endTime":"Sun, Aug 16, 2020 11:55 PM +0000","length":37200},{"streamer":"Lana_Lux","startTime":"Mon, Aug 17, 2020 1:16 PM +0000","endTime":"Mon, Aug 17, 2020 10:55 PM +0000","length":34743},{"streamer":"Lana_Lux","startTime":"Tue, Aug 18, 2020 2:10 PM +0000","endTime":"Tue, Aug 18, 2020 10:15 PM +0000","length":29099},{"streamer":"Lana_Lux","startTime":"Wed, Aug 19, 2020 1:35 PM +0000","endTime":"Wed, Aug 19, 2020 9:55 PM +0000","length":30000},{"streamer":"Lana_Lux","startTime":"Thu, Aug 20, 2020 2:35 PM +0000","endTime":"Thu, Aug 20, 2020 9:10 PM +0000","length":23699},{"streamer":"Lana_Lux","startTime":"Fri, Aug 21, 2020 3:10 PM +0000","endTime":"Fri, Aug 21, 2020 10:45 PM +0000","length":27300},{"streamer":"Lana_Lux","startTime":"Sat, Aug 22, 2020 2:15 PM +0000","endTime":"Sat, Aug 22, 2020 5:30 PM +0000","length":11701}],"JamesMontemagno":[{"streamer":"JamesMontemagno","startTime":"Fri, Aug 21, 2020 4:00 PM +0000","endTime":"Fri, Aug 21, 2020 6:15 PM +0000","length":8100}],"CodeRushed":[{"streamer":"CodeRushed","startTime":"Tue, Aug 18, 2020 4:05 PM +0000","endTime":"Tue, Aug 18, 2020 8:50 PM +0000","length":17099},{"streamer":"CodeRushed","startTime":"Wed, Aug 19, 2020 4:05 PM +0000","endTime":"Wed, Aug 19, 2020 8:10 PM +0000","length":14701},{"streamer":"CodeRushed","startTime":"Thu, Aug 20, 2020 4:10 PM +0000","endTime":"Thu, Aug 20, 2020 7:50 PM +0000","length":13200},{"streamer":"CodeRushed","startTime":"Fri, Aug 21, 2020 4:05 PM +0000","endTime":"Fri, Aug 21, 2020 5:55 PM +0000","length":6599}],"Clarkio":[{"streamer":"Clarkio","startTime":"Thu, Aug 20, 2020 2:00 PM +0000","endTime":"Thu, Aug 20, 2020 3:50 PM +0000","length":6600},{"streamer":"Clarkio","startTime":"Fri, Aug 21, 2020 4:35 PM +0000","endTime":"Fri, Aug 21, 2020 9:35 PM +0000","length":18001}],"Instafluff":[{"streamer":"Instafluff","startTime":"Sun, Aug 16, 2020 7:45 AM +0000","endTime":"Sun, Aug 16, 2020 6:40 PM +0000","length":39300},{"streamer":"Instafluff","startTime":"Wed, Aug 19, 2020 4:20 PM +0000","endTime":"Wed, Aug 19, 2020 9:15 PM +0000","length":17700},{"streamer":"Instafluff","startTime":"Thu, Aug 20, 2020 4:15 PM +0000","endTime":"Thu, Aug 20, 2020 9:30 PM +0000","length":18901},{"streamer":"Instafluff","startTime":"Fri, Aug 21, 2020 4:15 PM +0000","endTime":"Fri, Aug 21, 2020 8:25 PM +0000","length":15000},{"streamer":"Instafluff","startTime":"Sat, Aug 22, 2020 4:25 PM +0000","endTime":"Sat, Aug 22, 2020 9:25 PM +0000","length":18001}],"QualityCoder":[{"streamer":"QualityCoder","startTime":"Wed, Aug 19, 2020 2:25 AM +0000","endTime":"Wed, Aug 19, 2020 5:30 AM +0000","length":11100},{"streamer":"QualityCoder","startTime":"Fri, Aug 21, 2020 2:25 AM +0000","endTime":"Fri, Aug 21, 2020 4:25 AM +0000","length":7201},{"streamer":"QualityCoder","startTime":"Sat, Aug 22, 2020 3:05 AM +0000","endTime":"Sat, Aug 22, 2020 6:15 AM +0000","length":11400}],"sorskoot":[{"streamer":"sorskoot","startTime":"Mon, Aug 17, 2020 7:15 PM +0000","endTime":"Mon, Aug 17, 2020 10:05 PM +0000","length":10201},{"streamer":"sorskoot","startTime":"Thu, Aug 20, 2020 7:20 PM +0000","endTime":"Thu, Aug 20, 2020 10:15 PM +0000","length":10500}],"javidx9":[{"streamer":"javidx9","startTime":"Sun, Aug 16, 2020 4:55 PM +0000","endTime":"Sun, Aug 16, 2020 8:15 PM +0000","length":11999}],"illuminatedSpace":[{"streamer":"illuminatedSpace","startTime":"Tue, Aug 18, 2020 1:20 AM +0000","endTime":"Tue, Aug 18, 2020 3:45 AM +0000","length":8700},{"streamer":"illuminatedSpace","startTime":"Sat, Aug 22, 2020 2:15 PM +0000","endTime":"Sat, Aug 22, 2020 5:00 PM +0000","length":9901}],"potatoqualitee":[{"streamer":"potatoqualitee","startTime":"Tue, Aug 18, 2020 8:15 PM +0000","endTime":"Tue, Aug 18, 2020 10:45 PM +0000","length":9000}],"BaldBeardedBuilder":[{"streamer":"BaldBeardedBuilder","startTime":"Tue, Aug 18, 2020 6:05 PM +0000","endTime":"Tue, Aug 18, 2020 10:05 PM +0000","length":14400},{"streamer":"BaldBeardedBuilder","startTime":"Wed, Aug 19, 2020 6:05 PM +0000","endTime":"Wed, Aug 19, 2020 9:25 PM +0000","length":12000},{"streamer":"BaldBeardedBuilder","startTime":"Thu, Aug 20, 2020 6:05 PM +0000","endTime":"Fri, Aug 21, 2020 12:00 midnight +0000","length":21300}],"noopkat":[{"streamer":"noopkat","startTime":"Sun, Aug 16, 2020 4:00 PM +0000","endTime":"Sun, Aug 16, 2020 6:05 PM +0000","length":7499}],"csharpfritz":[{"streamer":"csharpfritz","startTime":"Sun, Aug 16, 2020 2:00 PM +0000","endTime":"Sun, Aug 16, 2020 5:05 PM +0000","length":11100},{"streamer":"csharpfritz","startTime":"Tue, Aug 18, 2020 1:05 PM +0000","endTime":"Tue, Aug 18, 2020 5:10 PM +0000","length":14700},{"streamer":"csharpfritz","startTime":"Thu, Aug 20, 2020 1:05 PM +0000","endTime":"Thu, Aug 20, 2020 4:40 PM +0000","length":12900}],"TimBeaudet":[{"streamer":"TimBeaudet","startTime":"Sun, Aug 16, 2020 10:15 AM +0000","endTime":"Sun, Aug 16, 2020 6:30 PM +0000","length":29699},{"streamer":"TimBeaudet","startTime":"Sun, Aug 16, 2020 9:40 PM +0000","endTime":"Mon, Aug 17, 2020 12:40 midnight +0000","length":10800},{"streamer":"TimBeaudet","startTime":"Mon, Aug 17, 2020 10:00 AM +0000","endTime":"Mon, Aug 17, 2020 1:15 PM +0000","length":11701},{"streamer":"TimBeaudet","startTime":"Tue, Aug 18, 2020 10:05 AM +0000","endTime":"Tue, Aug 18, 2020 12:10 noon +0000","length":7499},{"streamer":"TimBeaudet","startTime":"Tue, Aug 18, 2020 9:10 PM +0000","endTime":"Wed, Aug 19, 2020 12:15 midnight +0000","length":11099},{"streamer":"TimBeaudet","startTime":"Wed, Aug 19, 2020 10:15 AM +0000","endTime":"Wed, Aug 19, 2020 1:20 PM +0000","length":11099},{"streamer":"TimBeaudet","startTime":"Wed, Aug 19, 2020 9:05 PM +0000","endTime":"Thu, Aug 20, 2020 1:10 AM +0000","length":14700},{"streamer":"TimBeaudet","startTime":"Thu, Aug 20, 2020 10:05 AM +0000","endTime":"Thu, Aug 20, 2020 1:30 PM +0000","length":12300},{"streamer":"TimBeaudet","startTime":"Fri, Aug 21, 2020 10:05 AM +0000","endTime":"Fri, Aug 21, 2020 1:15 PM +0000","length":11401},{"streamer":"TimBeaudet","startTime":"Sat, Aug 22, 2020 10:15 AM +0000","endTime":"Sat, Aug 22, 2020 5:35 PM +0000","length":26400}],"codephobia":[{"streamer":"codephobia","startTime":"Mon, Aug 17, 2020 3:20 PM +0000","endTime":"Mon, Aug 17, 2020 8:40 PM +0000","length":19201},{"streamer":"codephobia","startTime":"Thu, Aug 20, 2020 5:20 PM +0000","endTime":"Thu, Aug 20, 2020 11:45 PM +0000","length":23100},{"streamer":"codephobia","startTime":"Fri, Aug 21, 2020 11:20 PM +0000","endTime":"Sat, Aug 22, 2020 5:40 AM +0000","length":22799}],"gep13":[{"streamer":"gep13","startTime":"Mon, Aug 17, 2020 7:00 PM +0000","endTime":"Mon, Aug 17, 2020 9:25 PM +0000","length":8701}],"VexFX":[{"streamer":"VexFX","startTime":"Tue, Aug 18, 2020 1:15 AM +0000","endTime":"Tue, Aug 18, 2020 10:40 AM +0000","length":33900},{"streamer":"VexFX","startTime":"Wed, Aug 19, 2020 1:15 AM +0000","endTime":"Wed, Aug 19, 2020 10:10 AM +0000","length":32099},{"streamer":"VexFX","startTime":"Thu, Aug 20, 2020 1:20 AM +0000","endTime":"Thu, Aug 20, 2020 9:30 AM +0000","length":29401},{"streamer":"VexFX","startTime":"Fri, Aug 21, 2020 1:55 AM +0000","endTime":"Fri, Aug 21, 2020 11:00 AM +0000","length":32700},{"streamer":"VexFX","startTime":"Sat, Aug 22, 2020 1:55 AM +0000","endTime":"Sat, Aug 22, 2020 12:05 noon +0000","length":36599}],"HonestDanGames":[{"streamer":"HonestDanGames","startTime":"Sun, Aug 16, 2020 12:30 noon +0000","endTime":"Sun, Aug 16, 2020 6:00 PM +0000","length":19801},{"streamer":"HonestDanGames","startTime":"Tue, Aug 18, 2020 4:10 PM +0000","endTime":"Tue, Aug 18, 2020 9:30 PM +0000","length":19200},{"streamer":"HonestDanGames","startTime":"Thu, Aug 20, 2020 5:00 PM +0000","endTime":"Thu, Aug 20, 2020 8:10 PM +0000","length":11401}],"LuckyNoS7evin":[{"streamer":"LuckyNoS7evin","startTime":"Sun, Aug 16, 2020 8:10 PM +0000","endTime":"Sun, Aug 16, 2020 11:25 PM +0000","length":11700}],"PixelogicDev":[{"streamer":"PixelogicDev","startTime":"Tue, Aug 18, 2020 12:20 noon +0000","endTime":"Tue, Aug 18, 2020 3:15 PM +0000","length":10499},{"streamer":"PixelogicDev","startTime":"Sat, Aug 22, 2020 6:05 PM +0000","endTime":"Sat, Aug 22, 2020 8:55 PM +0000","length":10199}],"JoshKupka":[{"streamer":"JoshKupka","startTime":"Mon, Aug 17, 2020 2:25 PM +0000","endTime":"Mon, Aug 17, 2020 3:15 PM +0000","length":3001},{"streamer":"JoshKupka","startTime":"Tue, Aug 18, 2020 7:15 PM +0000","endTime":"Tue, Aug 18, 2020 8:30 PM +0000","length":4499},{"streamer":"JoshKupka","startTime":"Wed, Aug 19, 2020 1:30 AM +0000","endTime":"Wed, Aug 19, 2020 5:40 AM +0000","length":15000},{"streamer":"JoshKupka","startTime":"Thu, Aug 20, 2020 12:00 midnight +0000","endTime":"Thu, Aug 20, 2020 3:55 AM +0000","length":14100},{"streamer":"JoshKupka","startTime":"Fri, Aug 21, 2020 2:10 AM +0000","endTime":"Fri, Aug 21, 2020 6:15 AM +0000","length":14700},{"streamer":"JoshKupka","startTime":"Sun, Aug 23, 2020 2:45 AM +0000","endTime":"Sun, Aug 23, 2020 5:05 AM +0000","length":8399}],"stuyksoft":[{"streamer":"stuyksoft","startTime":"Wed, Aug 19, 2020 5:05 PM +0000","endTime":"Wed, Aug 19, 2020 7:40 PM +0000","length":9301}],"ThePrimeagen":[{"streamer":"ThePrimeagen","startTime":"Mon, Aug 17, 2020 1:50 AM +0000","endTime":"Mon, Aug 17, 2020 6:10 AM +0000","length":15601},{"streamer":"ThePrimeagen","startTime":"Tue, Aug 18, 2020 2:10 AM +0000","endTime":"Tue, Aug 18, 2020 9:05 AM +0000","length":24900},{"streamer":"ThePrimeagen","startTime":"Thu, Aug 20, 2020 4:45 PM +0000","endTime":"Thu, Aug 20, 2020 9:15 PM +0000","length":16201},{"streamer":"ThePrimeagen","startTime":"Fri, Aug 21, 2020 12:30 midnight +0000","endTime":"Fri, Aug 21, 2020 3:25 AM +0000","length":10499},{"streamer":"ThePrimeagen","startTime":"Fri, Aug 21, 2020 6:25 PM +0000","endTime":"Fri, Aug 21, 2020 10:00 PM +0000","length":12899},{"streamer":"ThePrimeagen","startTime":"Sun, Aug 23, 2020 12:00 midnight +0000","endTime":"Sun, Aug 23, 2020 4:05 AM +0000","length":14700}],"Seekaplayer":[{"streamer":"Seekaplayer","startTime":"Sun, Aug 16, 2020 5:00 PM +0000","endTime":"Sun, Aug 16, 2020 5:25 PM +0000","length":1501},{"streamer":"Seekaplayer","startTime":"Mon, Aug 17, 2020 12:25 noon +0000","endTime":"Mon, Aug 17, 2020 2:10 PM +0000","length":6300},{"streamer":"Seekaplayer","startTime":"Tue, Aug 18, 2020 8:45 AM +0000","endTime":"Tue, Aug 18, 2020 10:45 AM +0000","length":7200},{"streamer":"Seekaplayer","startTime":"Thu, Aug 20, 2020 9:20 AM +0000","endTime":"Thu, Aug 20, 2020 11:40 AM +0000","length":8399},{"streamer":"Seekaplayer","startTime":"Sat, Aug 22, 2020 11:00 AM +0000","endTime":"Sat, Aug 22, 2020 1:50 PM +0000","length":10200},{"streamer":"Seekaplayer","startTime":"Sat, Aug 22, 2020 4:50 PM +0000","endTime":"Sat, Aug 22, 2020 9:55 PM +0000","length":18300}],"grahamweldon":[{"streamer":"grahamweldon","startTime":"Sun, Aug 16, 2020 7:45 AM +0000","endTime":"Sun, Aug 16, 2020 8:20 AM +0000","length":2100},{"streamer":"grahamweldon","startTime":"Fri, Aug 21, 2020 10:45 AM +0000","endTime":"Fri, Aug 21, 2020 5:30 PM +0000","length":24301}],"jfversluis":[{"streamer":"jfversluis","startTime":"Thu, Aug 20, 2020 6:25 PM +0000","endTime":"Thu, Aug 20, 2020 8:41 PM +0000","length":8154}],"FBoucheros":[{"streamer":"FBoucheros","startTime":"Wed, Aug 19, 2020 12:56 noon +0000","endTime":"Wed, Aug 19, 2020 3:00 PM +0000","length":7446},{"streamer":"FBoucheros","startTime":"Fri, Aug 21, 2020 1:05 PM +0000","endTime":"Fri, Aug 21, 2020 3:30 PM +0000","length":8700}],"TrezyCodes":[{"streamer":"TrezyCodes","startTime":"Wed, Aug 19, 2020 1:55 AM +0000","endTime":"Wed, Aug 19, 2020 9:00 AM +0000","length":25499},{"streamer":"TrezyCodes","startTime":"Thu, Aug 20, 2020 7:00 PM +0000","endTime":"Thu, Aug 20, 2020 8:10 PM +0000","length":4200}],"BrianLagunas":[{"streamer":"BrianLagunas","startTime":"Thu, Aug 20, 2020 3:55 PM +0000","endTime":"Thu, Aug 20, 2020 6:25 PM +0000","length":8999}],"jlengstorf":[{"streamer":"jlengstorf","startTime":"Tue, Aug 18, 2020 5:30 PM +0000","endTime":"Tue, Aug 18, 2020 7:00 PM +0000","length":5400},{"streamer":"jlengstorf","startTime":"Thu, Aug 20, 2020 4:30 PM +0000","endTime":"Thu, Aug 20, 2020 6:20 PM +0000","length":6599}],"trevorblades":[{"streamer":"trevorblades","startTime":"Tue, Aug 18, 2020 9:00 PM +0000","endTime":"Tue, Aug 18, 2020 10:05 PM +0000","length":3900},{"streamer":"trevorblades","startTime":"Tue, Aug 18, 2020 10:40 PM +0000","endTime":"Wed, Aug 19, 2020 1:00 AM +0000","length":8400},{"streamer":"trevorblades","startTime":"Thu, Aug 20, 2020 2:40 AM +0000","endTime":"Thu, Aug 20, 2020 4:45 AM +0000","length":7499}],"caLLowCreation":[{"streamer":"caLLowCreation","startTime":"Tue, Aug 18, 2020 9:00 PM +0000","endTime":"Wed, Aug 19, 2020 6:30 AM +0000","length":34199},{"streamer":"caLLowCreation","startTime":"Wed, Aug 19, 2020 9:05 PM +0000","endTime":"Thu, Aug 20, 2020 6:25 AM +0000","length":33599},{"streamer":"caLLowCreation","startTime":"Thu, Aug 20, 2020 9:20 PM +0000","endTime":"Fri, Aug 21, 2020 6:50 AM +0000","length":34200},{"streamer":"caLLowCreation","startTime":"Fri, Aug 21, 2020 9:10 PM +0000","endTime":"Sat, Aug 22, 2020 6:45 AM +0000","length":34501}],"CopperBeardy":[{"streamer":"CopperBeardy","startTime":"Mon, Aug 17, 2020 6:55 AM +0000","endTime":"Mon, Aug 17, 2020 10:00 AM +0000","length":11099},{"streamer":"CopperBeardy","startTime":"Mon, Aug 17, 2020 12:00 noon +0000","endTime":"Mon, Aug 17, 2020 2:15 PM +0000","length":8100},{"streamer":"CopperBeardy","startTime":"Wed, Aug 19, 2020 6:55 AM +0000","endTime":"Wed, Aug 19, 2020 10:00 AM +0000","length":11099},{"streamer":"CopperBeardy","startTime":"Wed, Aug 19, 2020 10:55 AM +0000","endTime":"Wed, Aug 19, 2020 1:55 PM +0000","length":10800},{"streamer":"CopperBeardy","startTime":"Thu, Aug 20, 2020 6:55 AM +0000","endTime":"Thu, Aug 20, 2020 10:00 AM +0000","length":11100},{"streamer":"CopperBeardy","startTime":"Thu, Aug 20, 2020 11:55 AM +0000","endTime":"Thu, Aug 20, 2020 1:35 PM +0000","length":6001},{"streamer":"CopperBeardy","startTime":"Sat, Aug 22, 2020 7:55 AM +0000","endTime":"Sat, Aug 22, 2020 10:05 AM +0000","length":7800}],"howtocodewell":[{"streamer":"howtocodewell","startTime":"Sun, Aug 16, 2020 1:30 PM +0000","endTime":"Sun, Aug 16, 2020 6:15 PM +0000","length":17101},{"streamer":"howtocodewell","startTime":"Tue, Aug 18, 2020 6:00 AM +0000","endTime":"Tue, Aug 18, 2020 7:35 AM +0000","length":5700},{"streamer":"howtocodewell","startTime":"Thu, Aug 20, 2020 8:05 PM +0000","endTime":"Thu, Aug 20, 2020 9:50 PM +0000","length":6301}],"tbdgamer":[{"streamer":"tbdgamer","startTime":"Tue, Aug 18, 2020 11:50 PM +0000","endTime":"Wed, Aug 19, 2020 3:55 AM +0000","length":14700},{"streamer":"tbdgamer","startTime":"Thu, Aug 20, 2020 11:40 PM +0000","endTime":"Fri, Aug 21, 2020 4:00 AM +0000","length":15601}],"zerratar":[{"streamer":"zerratar","startTime":"Mon, Aug 17, 2020 4:00 PM +0000","endTime":"Tue, Aug 18, 2020 9:35 PM +0000","length":106499},{"streamer":"zerratar","startTime":"Wed, Aug 19, 2020 8:20 PM +0000","endTime":"Wed, Aug 19, 2020 11:20 PM +0000","length":10799},{"streamer":"zerratar","startTime":"Thu, Aug 20, 2020 5:10 PM +0000","endTime":"Thu, Aug 20, 2020 8:45 PM +0000","length":12900}],"Zorchenhimer":[{"streamer":"Zorchenhimer","startTime":"Sun, Aug 16, 2020 10:30 PM +0000","endTime":"Mon, Aug 17, 2020 2:05 AM +0000","length":12900},{"streamer":"Zorchenhimer","startTime":"Wed, Aug 19, 2020 10:40 PM +0000","endTime":"Thu, Aug 20, 2020 1:40 AM +0000","length":10799},{"streamer":"Zorchenhimer","startTime":"Fri, Aug 21, 2020 10:45 PM +0000","endTime":"Sat, Aug 22, 2020 2:10 AM +0000","length":12300}],"albericod":[{"streamer":"albericod","startTime":"Thu, Aug 20, 2020 5:20 PM +0000","endTime":"Thu, Aug 20, 2020 10:05 PM +0000","length":17099}],"Fr33maan":[{"streamer":"Fr33maan","startTime":"Sat, Aug 22, 2020 8:00 AM +0000","endTime":"Sat, Aug 22, 2020 10:55 AM +0000","length":10501},{"streamer":"Fr33maan","startTime":"Sat, Aug 22, 2020 1:05 PM +0000","endTime":"Sat, Aug 22, 2020 3:35 PM +0000","length":9000}],"JesseSkinner":[{"streamer":"JesseSkinner","startTime":"Tue, Aug 18, 2020 5:05 PM +0000","endTime":"Tue, Aug 18, 2020 8:25 PM +0000","length":12001}],"Linuxgurugamer":[{"streamer":"Linuxgurugamer","startTime":"Sun, Aug 16, 2020 10:25 PM +0000","endTime":"Mon, Aug 17, 2020 4:35 AM +0000","length":22201},{"streamer":"Linuxgurugamer","startTime":"Mon, Aug 17, 2020 10:25 PM +0000","endTime":"Tue, Aug 18, 2020 4:45 AM +0000","length":22800},{"streamer":"Linuxgurugamer","startTime":"Tue, Aug 18, 2020 7:35 PM +0000","endTime":"Wed, Aug 19, 2020 4:30 AM +0000","length":32100},{"streamer":"Linuxgurugamer","startTime":"Wed, Aug 19, 2020 11:15 AM +0000","endTime":"Wed, Aug 19, 2020 7:25 PM +0000","length":29401},{"streamer":"Linuxgurugamer","startTime":"Thu, Aug 20, 2020 12:10 noon +0000","endTime":"Fri, Aug 21, 2020 11:20 AM +0000","length":83400},{"streamer":"Linuxgurugamer","startTime":"Fri, Aug 21, 2020 4:50 PM +0000","endTime":"Fri, Aug 21, 2020 8:35 PM +0000","length":13500}],"TutorExilius":[{"streamer":"TutorExilius","startTime":"Sun, Aug 16, 2020 3:30 PM +0000","endTime":"Sun, Aug 16, 2020 6:30 PM +0000","length":10800},{"streamer":"TutorExilius","startTime":"Mon, Aug 17, 2020 12:10 noon +0000","endTime":"Mon, Aug 17, 2020 3:40 PM +0000","length":12601},{"streamer":"TutorExilius","startTime":"Mon, Aug 17, 2020 6:55 PM +0000","endTime":"Mon, Aug 17, 2020 9:00 PM +0000","length":7499},{"streamer":"TutorExilius","startTime":"Tue, Aug 18, 2020 10:15 AM +0000","endTime":"Tue, Aug 18, 2020 3:15 PM +0000","length":17999},{"streamer":"TutorExilius","startTime":"Wed, Aug 19, 2020 12:25 noon +0000","endTime":"Wed, Aug 19, 2020 4:40 PM +0000","length":15301}],"sadmoody":[{"streamer":"sadmoody","startTime":"Tue, Aug 18, 2020 7:10 AM +0000","endTime":"Tue, Aug 18, 2020 10:30 AM +0000","length":12000},{"streamer":"sadmoody","startTime":"Thu, Aug 20, 2020 7:20 AM +0000","endTime":"Thu, Aug 20, 2020 10:55 AM +0000","length":12900}],"Acegikmo":[{"streamer":"Acegikmo","startTime":"Thu, Aug 20, 2020 3:40 PM +0000","endTime":"Thu, Aug 20, 2020 7:50 PM +0000","length":15000},{"streamer":"Acegikmo","startTime":"Fri, Aug 21, 2020 3:25 PM +0000","endTime":"Fri, Aug 21, 2020 6:50 PM +0000","length":12300},{"streamer":"Acegikmo","startTime":"Sat, Aug 22, 2020 3:35 PM +0000","endTime":"Sat, Aug 22, 2020 8:00 PM +0000","length":15901}],"LarryNY":[{"streamer":"LarryNY","startTime":"Mon, Aug 17, 2020 1:25 AM +0000","endTime":"Mon, Aug 17, 2020 4:15 AM +0000","length":10200}],"nopogo_tv":[{"streamer":"nopogo_tv","startTime":"Wed, Aug 19, 2020 9:40 AM +0000","endTime":"Wed, Aug 19, 2020 3:25 PM +0000","length":20700},{"streamer":"nopogo_tv","startTime":"Fri, Aug 21, 2020 9:05 AM +0000","endTime":"Fri, Aug 21, 2020 3:40 PM +0000","length":23699}],"beginbot":[{"streamer":"beginbot","startTime":"Sun, Aug 16, 2020 4:55 PM +0000","endTime":"Sun, Aug 16, 2020 9:45 PM +0000","length":17400},{"streamer":"beginbot","startTime":"Mon, Aug 17, 2020 1:00 PM +0000","endTime":"Mon, Aug 17, 2020 4:50 PM +0000","length":13801},{"streamer":"beginbot","startTime":"Tue, Aug 18, 2020 1:00 PM +0000","endTime":"Tue, Aug 18, 2020 4:40 PM +0000","length":13200},{"streamer":"beginbot","startTime":"Wed, Aug 19, 2020 1:00 PM +0000","endTime":"Wed, Aug 19, 2020 2:00 PM +0000","length":3600},{"streamer":"beginbot","startTime":"Thu, Aug 20, 2020 1:00 PM +0000","endTime":"Thu, Aug 20, 2020 4:50 PM +0000","length":13801},{"streamer":"beginbot","startTime":"Fri, Aug 21, 2020 1:00 PM +0000","endTime":"Fri, Aug 21, 2020 4:45 PM +0000","length":13499}],"SlevinthHeaven":[{"streamer":"SlevinthHeaven","startTime":"Thu, Aug 20, 2020 6:30 PM +0000","endTime":"Thu, Aug 20, 2020 9:55 PM +0000","length":12300}],"JessicaMak":[{"streamer":"JessicaMak","startTime":"Wed, Aug 19, 2020 1:50 PM +0000","endTime":"Wed, Aug 19, 2020 7:45 PM +0000","length":21300},{"streamer":"JessicaMak","startTime":"Thu, Aug 20, 2020 6:10 PM +0000","endTime":"Thu, Aug 20, 2020 10:55 PM +0000","length":17100}],"CodingGarden":[{"streamer":"CodingGarden","startTime":"Mon, Aug 17, 2020 1:40 PM +0000","endTime":"Mon, Aug 17, 2020 4:10 PM +0000","length":9000},{"streamer":"CodingGarden","startTime":"Wed, Aug 19, 2020 1:40 PM +0000","endTime":"Wed, Aug 19, 2020 4:20 PM +0000","length":9599},{"streamer":"CodingGarden","startTime":"Fri, Aug 21, 2020 2:30 PM +0000","endTime":"Fri, Aug 21, 2020 11:40 PM +0000","length":32999}],"anthonywritescode":[{"streamer":"anthonywritescode","startTime":"Mon, Aug 17, 2020 6:55 PM +0000","endTime":"Mon, Aug 17, 2020 11:20 PM +0000","length":15899},{"streamer":"anthonywritescode","startTime":"Thu, Aug 20, 2020 7:00 PM +0000","endTime":"Thu, Aug 20, 2020 11:20 PM +0000","length":15600},{"streamer":"anthonywritescode","startTime":"Fri, Aug 21, 2020 7:00 PM +0000","endTime":"Fri, Aug 21, 2020 10:00 PM +0000","length":10800},{"streamer":"anthonywritescode","startTime":"Sat, Aug 22, 2020 7:00 PM +0000","endTime":"Sat, Aug 22, 2020 10:45 PM +0000","length":13499}],"TheGrumpyGameDev":[{"streamer":"TheGrumpyGameDev","startTime":"Sun, Aug 16, 2020 9:20 AM +0000","endTime":"Sun, Aug 16, 2020 11:50 AM +0000","length":9000},{"streamer":"TheGrumpyGameDev","startTime":"Mon, Aug 17, 2020 9:30 AM +0000","endTime":"Mon, Aug 17, 2020 11:35 AM +0000","length":7500},{"streamer":"TheGrumpyGameDev","startTime":"Tue, Aug 18, 2020 9:30 AM +0000","endTime":"Tue, Aug 18, 2020 11:30 AM +0000","length":7201},{"streamer":"TheGrumpyGameDev","startTime":"Wed, Aug 19, 2020 9:15 AM +0000","endTime":"Wed, Aug 19, 2020 11:30 AM +0000","length":8099},{"streamer":"TheGrumpyGameDev","startTime":"Thu, Aug 20, 2020 9:30 AM +0000","endTime":"Thu, Aug 20, 2020 10:50 AM +0000","length":4800},{"streamer":"TheGrumpyGameDev","startTime":"Fri, Aug 21, 2020 9:25 AM +0000","endTime":"Fri, Aug 21, 2020 11:35 AM +0000","length":7799},{"streamer":"TheGrumpyGameDev","startTime":"Sat, Aug 22, 2020 9:05 AM +0000","endTime":"Sat, Aug 22, 2020 11:10 AM +0000","length":7500}],"FrankKrueger":[{"streamer":"FrankKrueger","startTime":"Sun, Aug 16, 2020 5:00 PM +0000","endTime":"Sun, Aug 16, 2020 10:45 PM +0000","length":20701}],"Krassenstein":[{"streamer":"Krassenstein","startTime":"Sun, Aug 16, 2020 10:15 AM +0000","endTime":"Sun, Aug 16, 2020 1:00 PM +0000","length":9899},{"streamer":"Krassenstein","startTime":"Mon, Aug 17, 2020 9:15 AM +0000","endTime":"Mon, Aug 17, 2020 11:55 AM +0000","length":9600},{"streamer":"Krassenstein","startTime":"Tue, Aug 18, 2020 9:30 AM +0000","endTime":"Tue, Aug 18, 2020 12:20 noon +0000","length":10201},{"streamer":"Krassenstein","startTime":"Wed, Aug 19, 2020 10:05 AM +0000","endTime":"Wed, Aug 19, 2020 12:35 noon +0000","length":9000},{"streamer":"Krassenstein","startTime":"Thu, Aug 20, 2020 9:40 AM +0000","endTime":"Thu, Aug 20, 2020 12:15 noon +0000","length":9301},{"streamer":"Krassenstein","startTime":"Fri, Aug 21, 2020 9:50 AM +0000","endTime":"Fri, Aug 21, 2020 12:35 noon +0000","length":9900},{"streamer":"Krassenstein","startTime":"Sat, Aug 22, 2020 10:20 AM +0000","endTime":"Sat, Aug 22, 2020 12:15 noon +0000","length":6900},{"streamer":"Krassenstein","startTime":"Sun, Aug 23, 2020 2:25 AM +0000","endTime":"Sun, Aug 23, 2020 3:45 AM +0000","length":4799}],"DavidWengier":[{"streamer":"DavidWengier","startTime":"Wed, Aug 19, 2020 10:30 AM +0000","endTime":"Wed, Aug 19, 2020 12:20 noon +0000","length":6601}],"marcobrunodev":[{"streamer":"marcobrunodev","startTime":"Mon, Aug 17, 2020 6:00 PM +0000","endTime":"Mon, Aug 17, 2020 9:15 PM +0000","length":11700},{"streamer":"marcobrunodev","startTime":"Tue, Aug 18, 2020 12:50 noon +0000","endTime":"Tue, Aug 18, 2020 9:25 PM +0000","length":30900},{"streamer":"marcobrunodev","startTime":"Fri, Aug 21, 2020 12:00 noon +0000","endTime":"Fri, Aug 21, 2020 3:20 PM +0000","length":12000},{"streamer":"marcobrunodev","startTime":"Sat, Aug 22, 2020 8:40 PM +0000","endTime":"Sat, Aug 22, 2020 11:30 PM +0000","length":10200}],"Spherous":[{"streamer":"Spherous","startTime":"Wed, Aug 19, 2020 8:00 PM +0000","endTime":"Thu, Aug 20, 2020 2:05 AM +0000","length":21900},{"streamer":"Spherous","startTime":"Thu, Aug 20, 2020 8:05 PM +0000","endTime":"Fri, Aug 21, 2020 2:45 AM +0000","length":24001},{"streamer":"Spherous","startTime":"Fri, Aug 21, 2020 8:05 PM +0000","endTime":"Fri, Aug 21, 2020 8:30 PM +0000","length":1501},{"streamer":"Spherous","startTime":"Sat, Aug 22, 2020 8:05 PM +0000","endTime":"Sun, Aug 23, 2020 2:10 AM +0000","length":21901}],"AshleeMBoyer":[{"streamer":"AshleeMBoyer","startTime":"Sun, Aug 16, 2020 7:25 PM +0000","endTime":"Sun, Aug 16, 2020 10:20 PM +0000","length":10500},{"streamer":"AshleeMBoyer","startTime":"Tue, Aug 18, 2020 11:10 PM +0000","endTime":"Wed, Aug 19, 2020 3:10 AM +0000","length":14399},{"streamer":"AshleeMBoyer","startTime":"Thu, Aug 20, 2020 11:45 PM +0000","endTime":"Fri, Aug 21, 2020 3:05 AM +0000","length":12001}],"ManningPublications":[{"streamer":"ManningPublications","startTime":"Tue, Aug 18, 2020 10:55 PM +0000","endTime":"Wed, Aug 19, 2020 12:30 midnight +0000","length":5700},{"streamer":"ManningPublications","startTime":"Wed, Aug 19, 2020 7:05 PM +0000","endTime":"Wed, Aug 19, 2020 8:25 PM +0000","length":4800},{"streamer":"ManningPublications","startTime":"Thu, Aug 20, 2020 9:05 PM +0000","endTime":"Thu, Aug 20, 2020 9:50 PM +0000","length":2700}],"Spacedevs":[{"streamer":"Spacedevs","startTime":"Sun, Aug 16, 2020 5:55 PM +0000","endTime":"Sun, Aug 16, 2020 7:30 PM +0000","length":5701}],"SaintPlaysThings":[{"streamer":"SaintPlaysThings","startTime":"Tue, Aug 18, 2020 3:55 PM +0000","endTime":"Tue, Aug 18, 2020 9:20 PM +0000","length":19500},{"streamer":"SaintPlaysThings","startTime":"Sat, Aug 22, 2020 5:40 PM +0000","endTime":"Sat, Aug 22, 2020 9:30 PM +0000","length":13800}],"Kaisinnel":[{"streamer":"Kaisinnel","startTime":"Wed, Aug 19, 2020 7:10 PM +0000","endTime":"Wed, Aug 19, 2020 8:45 PM +0000","length":5700}],"phil_nash":[{"streamer":"phil_nash","startTime":"Sun, Aug 16, 2020 11:55 PM +0000","endTime":"Mon, Aug 17, 2020 3:20 AM +0000","length":12301},{"streamer":"phil_nash","startTime":"Tue, Aug 18, 2020 12:05 midnight +0000","endTime":"Tue, Aug 18, 2020 2:40 AM +0000","length":9300}],"melkeydev":[{"streamer":"melkeydev","startTime":"Mon, Aug 17, 2020 11:40 PM +0000","endTime":"Tue, Aug 18, 2020 5:20 AM +0000","length":20400},{"streamer":"melkeydev","startTime":"Wed, Aug 19, 2020 11:25 PM +0000","endTime":"Thu, Aug 20, 2020 5:35 AM +0000","length":22201},{"streamer":"melkeydev","startTime":"Fri, Aug 21, 2020 8:15 PM +0000","endTime":"Sat, Aug 22, 2020 1:00 AM +0000","length":17099},{"streamer":"melkeydev","startTime":"Sat, Aug 22, 2020 4:20 PM +0000","endTime":"Sun, Aug 23, 2020 2:55 AM +0000","length":38100}],"Kruiser8":[{"streamer":"Kruiser8","startTime":"Mon, Aug 17, 2020 11:50 PM +0000","endTime":"Tue, Aug 18, 2020 3:30 AM +0000","length":13201},{"streamer":"Kruiser8","startTime":"Thu, Aug 20, 2020 12:05 midnight +0000","endTime":"Thu, Aug 20, 2020 3:15 AM +0000","length":11401},{"streamer":"Kruiser8","startTime":"Sat, Aug 22, 2020 12:10 midnight +0000","endTime":"Sat, Aug 22, 2020 3:55 AM +0000","length":13500}],"whitep4nth3r":[{"streamer":"whitep4nth3r","startTime":"Sun, Aug 16, 2020 5:45 PM +0000","endTime":"Sun, Aug 16, 2020 9:25 PM +0000","length":13199},{"streamer":"whitep4nth3r","startTime":"Tue, Aug 18, 2020 6:15 PM +0000","endTime":"Tue, Aug 18, 2020 8:50 PM +0000","length":9299},{"streamer":"whitep4nth3r","startTime":"Thu, Aug 20, 2020 5:50 PM +0000","endTime":"Thu, Aug 20, 2020 9:30 PM +0000","length":13200},{"streamer":"whitep4nth3r","startTime":"Fri, Aug 21, 2020 11:45 AM +0000","endTime":"Fri, Aug 21, 2020 4:00 PM +0000","length":15301},{"streamer":"whitep4nth3r","startTime":"Sat, Aug 22, 2020 12:10 noon +0000","endTime":"Sat, Aug 22, 2020 2:10 PM +0000","length":7201},{"streamer":"whitep4nth3r","startTime":"Sat, Aug 22, 2020 5:40 PM +0000","endTime":"Sat, Aug 22, 2020 9:35 PM +0000","length":14100}],"erikdotdev":[{"streamer":"erikdotdev","startTime":"Mon, Aug 17, 2020 4:45 PM +0000","endTime":"Mon, Aug 17, 2020 8:15 PM +0000","length":12600},{"streamer":"erikdotdev","startTime":"Wed, Aug 19, 2020 5:05 PM +0000","endTime":"Wed, Aug 19, 2020 8:55 PM +0000","length":13800},{"streamer":"erikdotdev","startTime":"Thu, Aug 20, 2020 5:30 PM +0000","endTime":"Thu, Aug 20, 2020 8:30 PM +0000","length":10800},{"streamer":"erikdotdev","startTime":"Sat, Aug 22, 2020 4:40 PM +0000","endTime":"Sat, Aug 22, 2020 8:15 PM +0000","length":12899},{"streamer":"erikdotdev","startTime":"Sat, Aug 22, 2020 9:01 PM +0000","endTime":"Sun, Aug 23, 2020 1:30 AM +0000","length":16145}],"mewtru":[{"streamer":"mewtru","startTime":"Sun, Aug 16, 2020 8:00 PM +0000","endTime":"Sun, Aug 16, 2020 9:55 PM +0000","length":6901},{"streamer":"mewtru","startTime":"Wed, Aug 19, 2020 2:30 AM +0000","endTime":"Wed, Aug 19, 2020 4:25 AM +0000","length":6901},{"streamer":"mewtru","startTime":"Fri, Aug 21, 2020 6:50 PM +0000","endTime":"Fri, Aug 21, 2020 9:20 PM +0000","length":8999}],"JdotW":[{"streamer":"JdotW","startTime":"Sun, Aug 16, 2020 11:05 PM +0000","endTime":"Mon, Aug 17, 2020 1:10 AM +0000","length":7501},{"streamer":"JdotW","startTime":"Mon, Aug 17, 2020 11:10 PM +0000","endTime":"Tue, Aug 18, 2020 1:45 AM +0000","length":9301},{"streamer":"JdotW","startTime":"Tue, Aug 18, 2020 11:15 PM +0000","endTime":"Wed, Aug 19, 2020 1:25 AM +0000","length":7800},{"streamer":"JdotW","startTime":"Wed, Aug 19, 2020 11:45 PM +0000","endTime":"Thu, Aug 20, 2020 2:05 AM +0000","length":8401},{"streamer":"JdotW","startTime":"Thu, Aug 20, 2020 11:05 PM +0000","endTime":"Fri, Aug 21, 2020 12:05 midnight +0000","length":3601}],"crazy4pi314":[{"streamer":"crazy4pi314","startTime":"Tue, Aug 18, 2020 5:00 PM +0000","endTime":"Tue, Aug 18, 2020 7:20 PM +0000","length":8400},{"streamer":"crazy4pi314","startTime":"Wed, Aug 19, 2020 5:00 PM +0000","endTime":"Wed, Aug 19, 2020 6:05 PM +0000","length":3899},{"streamer":"crazy4pi314","startTime":"Fri, Aug 21, 2020 5:05 PM +0000","endTime":"Fri, Aug 21, 2020 7:10 PM +0000","length":7499}],"nomadCodeMist":[{"streamer":"nomadCodeMist","startTime":"Tue, Aug 18, 2020 12:10 midnight +0000","endTime":"Tue, Aug 18, 2020 3:20 AM +0000","length":11400},{"streamer":"nomadCodeMist","startTime":"Wed, Aug 19, 2020 11:35 PM +0000","endTime":"Thu, Aug 20, 2020 2:15 AM +0000","length":9601},{"streamer":"nomadCodeMist","startTime":"Fri, Aug 21, 2020 11:40 PM +0000","endTime":"Sat, Aug 22, 2020 2:30 AM +0000","length":10200}],"ProfAHeil":[{"streamer":"ProfAHeil","startTime":"Mon, Aug 17, 2020 9:00 AM +0000","endTime":"Mon, Aug 17, 2020 10:55 AM +0000","length":6900},{"streamer":"ProfAHeil","startTime":"Mon, Aug 17, 2020 9:25 PM +0000","endTime":"Tue, Aug 18, 2020 12:05 midnight +0000","length":9600},{"streamer":"ProfAHeil","startTime":"Wed, Aug 19, 2020 7:10 AM +0000","endTime":"Wed, Aug 19, 2020 8:40 AM +0000","length":5401}],"SirLynixVanFrietjes":[{"streamer":"SirLynixVanFrietjes","startTime":"Sun, Aug 16, 2020 11:45 AM +0000","endTime":"Sun, Aug 16, 2020 5:20 PM +0000","length":20101},{"streamer":"SirLynixVanFrietjes","startTime":"Wed, Aug 19, 2020 3:25 PM +0000","endTime":"Wed, Aug 19, 2020 5:35 PM +0000","length":7799},{"streamer":"SirLynixVanFrietjes","startTime":"Thu, Aug 20, 2020 3:35 PM +0000","endTime":"Thu, Aug 20, 2020 5:35 PM +0000","length":7200},{"streamer":"SirLynixVanFrietjes","startTime":"Sat, Aug 22, 2020 2:00 PM +0000","endTime":"Sat, Aug 22, 2020 3:35 PM +0000","length":5700}],"GRSoares":[{"streamer":"GRSoares","startTime":"Mon, Aug 17, 2020 4:30 PM +0000","endTime":"Mon, Aug 17, 2020 6:20 PM +0000","length":6600},{"streamer":"GRSoares","startTime":"Tue, Aug 18, 2020 4:30 PM +0000","endTime":"Tue, Aug 18, 2020 6:30 PM +0000","length":7201},{"streamer":"GRSoares","startTime":"Thu, Aug 20, 2020 4:50 PM +0000","endTime":"Thu, Aug 20, 2020 6:20 PM +0000","length":5400}],"bdougieYO":[{"streamer":"bdougieYO","startTime":"Tue, Aug 18, 2020 9:05 PM +0000","endTime":"Wed, Aug 19, 2020 12:05 midnight +0000","length":10800},{"streamer":"bdougieYO","startTime":"Fri, Aug 21, 2020 1:10 PM +0000","endTime":"Fri, Aug 21, 2020 3:10 PM +0000","length":7200},{"streamer":"bdougieYO","startTime":"Fri, Aug 21, 2020 9:05 PM +0000","endTime":"Fri, Aug 21, 2020 11:25 PM +0000","length":8400}],"RenoInMO":[{"streamer":"RenoInMO","startTime":"Sun, Aug 16, 2020 2:15 PM +0000","endTime":"Sun, Aug 16, 2020 6:40 PM +0000","length":15900}],"teomewhy":[{"streamer":"teomewhy","startTime":"Tue, Aug 18, 2020 10:55 PM +0000","endTime":"Wed, Aug 19, 2020 1:20 AM +0000","length":8699},{"streamer":"teomewhy","startTime":"Thu, Aug 20, 2020 10:55 PM +0000","endTime":"Fri, Aug 21, 2020 1:10 AM +0000","length":8100},{"streamer":"teomewhy","startTime":"Sat, Aug 22, 2020 10:55 PM +0000","endTime":"Sun, Aug 23, 2020 3:00 AM +0000","length":14699}],"IrishJohnGaming":[{"streamer":"IrishJohnGaming","startTime":"Tue, Aug 18, 2020 6:05 PM +0000","endTime":"Tue, Aug 18, 2020 7:50 PM +0000","length":6300},{"streamer":"IrishJohnGaming","startTime":"Wed, Aug 19, 2020 6:20 PM +0000","endTime":"Wed, Aug 19, 2020 9:05 PM +0000","length":9901},{"streamer":"IrishJohnGaming","startTime":"Thu, Aug 20, 2020 4:00 PM +0000","endTime":"Thu, Aug 20, 2020 7:00 PM +0000","length":10801},{"streamer":"IrishJohnGaming","startTime":"Fri, Aug 21, 2020 6:35 PM +0000","endTime":"Fri, Aug 21, 2020 8:25 PM +0000","length":6600}],"XAMLLlama":[{"streamer":"XAMLLlama","startTime":"Mon, Aug 17, 2020 7:00 PM +0000","endTime":"Mon, Aug 17, 2020 9:15 PM +0000","length":8101},{"streamer":"XAMLLlama","startTime":"Tue, Aug 18, 2020 7:05 PM +0000","endTime":"Tue, Aug 18, 2020 11:00 PM +0000","length":14100},{"streamer":"XAMLLlama","startTime":"Wed, Aug 19, 2020 9:50 PM +0000","endTime":"Thu, Aug 20, 2020 12:15 midnight +0000","length":8700},{"streamer":"XAMLLlama","startTime":"Thu, Aug 20, 2020 4:35 PM +0000","endTime":"Thu, Aug 20, 2020 7:35 PM +0000","length":10799}],"ionixjunior":[{"streamer":"ionixjunior","startTime":"Wed, Aug 19, 2020 1:10 AM +0000","endTime":"Wed, Aug 19, 2020 2:10 AM +0000","length":3600},{"streamer":"ionixjunior","startTime":"Thu, Aug 20, 2020 11:10 PM +0000","endTime":"Fri, Aug 21, 2020 3:05 AM +0000","length":14100},{"streamer":"ionixjunior","startTime":"Sat, Aug 22, 2020 1:00 PM +0000","endTime":"Sat, Aug 22, 2020 4:15 PM +0000","length":11700}],"florinpop17":[{"streamer":"florinpop17","startTime":"Tue, Aug 18, 2020 3:45 PM +0000","endTime":"Tue, Aug 18, 2020 5:35 PM +0000","length":6600},{"streamer":"florinpop17","startTime":"Thu, Aug 20, 2020 3:10 PM +0000","endTime":"Thu, Aug 20, 2020 4:25 PM +0000","length":4499}]}
